monadicbox/__init__.py
monadicbox/monad.py
MonadicBox-0.0.1.dist-info/LICENSE
MonadicBox-0.0.1.dist-info/METADATA
MonadicBox-0.0.1.dist-info/WHEEL
MonadicBox-0.0.1.dist-info/top_level.txt
MonadicBox-0.0.1.dist-info/RECORD
