Metadata-Version: 2.1
Name: MonadicBox
Version: 0.0.1
Summary: Monads for python
Author: AkiSun
Project-URL: Homepage, https://github.com/AkiSun/monadicbox
Project-URL: Issues, https://github.com/AkiSun/monadicbox/issues
Classifier: Programming Language :: Python :: 3
Classifier: License :: OSI Approved :: MIT License
Classifier: Operating System :: OS Independent
Requires-Python: >=3.8
License-File: LICENSE
